<annotation>
	<folder>eye</folder>
	<filename>1 (2725).jpg</filename>
	<path>C:\Users\Dima\PycharmProjects\ai\Tensorflow\workspace\images\collectedimages\eye\1 (2725).jpg</path>
	<source>
		<database>Unknown</database>
	</source>
	<size>
		<width>3456</width>
		<height>2304</height>
		<depth>3</depth>
	</size>
	<segmented>0</segmented>
	<object>
		<name>eye</name>
		<pose>Unspecified</pose>
		<truncated>0</truncated>
		<difficult>0</difficult>
		<bndbox>
			<xmin>1756</xmin>
			<ymin>854</ymin>
			<xmax>2068</xmax>
			<ymax>1005</ymax>
		</bndbox>
	</object>
	<object>
		<name>eye</name>
		<pose>Unspecified</pose>
		<truncated>0</truncated>
		<difficult>0</difficult>
		<bndbox>
			<xmin>2224</xmin>
			<ymin>873</ymin>
			<xmax>2514</xmax>
			<ymax>1017</ymax>
		</bndbox>
	</object>
</annotation>
